profile_data_directory/__init__.py
profile_data_directory/copy_dataset_files.py
profile_data_directory/dataset_manager.py
profile_data_directory/file_utils.py
profile_data_directory/find_last.py
profile_data_directory/find_last_directory.py
profile_data_directory/find_last_file.py
profile_data_directory/manager.py
profile_data_directory/profile_data_directory.py
profile_data_directory/survey_dataset_directory.py
profile_data_directory/conf/config.yaml
profile_data_directory-0.2.1.dist-info/AUTHORS.rst
profile_data_directory-0.2.1.dist-info/LICENSE
profile_data_directory-0.2.1.dist-info/METADATA
profile_data_directory-0.2.1.dist-info/WHEEL
profile_data_directory-0.2.1.dist-info/entry_points.txt
profile_data_directory-0.2.1.dist-info/top_level.txt
profile_data_directory-0.2.1.dist-info/RECORD
