Metadata-Version: 2.1
Name: profile-data-directory
Version: 0.2.1
Summary: A package for profiling the files in a data directory
Home-page: https://github.com/jai-python3/profile-data-directory
Author: Jaideep Sundaram
Author-email: jai.python3@gmail.com
License: GNU General Public License v3
Keywords: profile_data_directory
Classifier: Development Status :: 2 - Pre-Alpha
Classifier: Intended Audience :: Developers
Classifier: License :: OSI Approved :: GNU General Public License v3 (GPLv3)
Classifier: Natural Language :: English
Classifier: Programming Language :: Python :: 3
Classifier: Programming Language :: Python :: 3.6
Classifier: Programming Language :: Python :: 3.7
Classifier: Programming Language :: Python :: 3.8
Requires-Python: >=3.6
License-File: LICENSE
License-File: AUTHORS.rst
Requires-Dist: Click >=7.0
Requires-Dist: Rich
Requires-Dist: PyYAML
